{
  "slug": "dating-strategy",
  "title": "연애 공략법",
  "type": "likert",
  "scale": "0-4",
  "category": "연애&결혼",
  "badge": "팁",
  "desc": "현실적인 연애 운영 전략을 점검합니다.",
  "questions": [
    {
      "id": "q1",
      "text": "첫 인상에서 강점을 드러낼 포인트를 준비한다",
      "options": [
        {
          "id": "a",
          "label": "전혀 아니다",
          "score": 0
        },
        {
          "id": "b",
          "label": "아니다",
          "score": 1
        },
        {
          "id": "c",
          "label": "보통이다",
          "score": 2
        },
        {
          "id": "d",
          "label": "그렇다",
          "score": 3
        },
        {
          "id": "e",
          "label": "매우 그렇다",
          "score": 4
        }
      ]
    },
    {
      "id": "q2",
      "text": "상대의 관심사 질문 리스트를 갖고 있다",
      "options": [
        {
          "id": "a",
          "label": "전혀 아니다",
          "score": 0
        },
        {
          "id": "b",
          "label": "아니다",
          "score": 1
        },
        {
          "id": "c",
          "label": "보통이다",
          "score": 2
        },
        {
          "id": "d",
          "label": "그렇다",
          "score": 3
        },
        {
          "id": "e",
          "label": "매우 그렇다",
          "score": 4
        }
      ]
    },
    {
      "id": "q3",
      "text": "연락 템포를 상황에 맞게 조절한다",
      "options": [
        {
          "id": "a",
          "label": "전혀 아니다",
          "score": 0
        },
        {
          "id": "b",
          "label": "아니다",
          "score": 1
        },
        {
          "id": "c",
          "label": "보통이다",
          "score": 2
        },
        {
          "id": "d",
          "label": "그렇다",
          "score": 3
        },
        {
          "id": "e",
          "label": "매우 그렇다",
          "score": 4
        }
      ]
    },
    {
      "id": "q4",
      "text": "데이트 후 피드백을 자연스럽게 주고받는다",
      "options": [
        {
          "id": "a",
          "label": "전혀 아니다",
          "score": 0
        },
        {
          "id": "b",
          "label": "아니다",
          "score": 1
        },
        {
          "id": "c",
          "label": "보통이다",
          "score": 2
        },
        {
          "id": "d",
          "label": "그렇다",
          "score": 3
        },
        {
          "id": "e",
          "label": "매우 그렇다",
          "score": 4
        }
      ]
    },
    {
      "id": "q5",
      "text": "감정 표현을 말/행동으로 구체화한다",
      "options": [
        {
          "id": "a",
          "label": "전혀 아니다",
          "score": 0
        },
        {
          "id": "b",
          "label": "아니다",
          "score": 1
        },
        {
          "id": "c",
          "label": "보통이다",
          "score": 2
        },
        {
          "id": "d",
          "label": "그렇다",
          "score": 3
        },
        {
          "id": "e",
          "label": "매우 그렇다",
          "score": 4
        }
      ]
    },
    {
      "id": "q6",
      "text": "갈등 시 타임아웃·재시도 규칙을 쓴다",
      "options": [
        {
          "id": "a",
          "label": "전혀 아니다",
          "score": 0
        },
        {
          "id": "b",
          "label": "아니다",
          "score": 1
        },
        {
          "id": "c",
          "label": "보통이다",
          "score": 2
        },
        {
          "id": "d",
          "label": "그렇다",
          "score": 3
        },
        {
          "id": "e",
          "label": "매우 그렇다",
          "score": 4
        }
      ]
    },
    {
      "id": "q7",
      "text": "중요한 기념일/이벤트를 챙긴다",
      "options": [
        {
          "id": "a",
          "label": "전혀 아니다",
          "score": 0
        },
        {
          "id": "b",
          "label": "아니다",
          "score": 1
        },
        {
          "id": "c",
          "label": "보통이다",
          "score": 2
        },
        {
          "id": "d",
          "label": "그렇다",
          "score": 3
        },
        {
          "id": "e",
          "label": "매우 그렇다",
          "score": 4
        }
      ]
    },
    {
      "id": "q8",
      "text": "친구·가족 경계를 존중한다",
      "options": [
        {
          "id": "a",
          "label": "전혀 아니다",
          "score": 0
        },
        {
          "id": "b",
          "label": "아니다",
          "score": 1
        },
        {
          "id": "c",
          "label": "보통이다",
          "score": 2
        },
        {
          "id": "d",
          "label": "그렇다",
          "score": 3
        },
        {
          "id": "e",
          "label": "매우 그렇다",
          "score": 4
        }
      ]
    },
    {
      "id": "q9",
      "text": "금전·시간 사용을 투명하게 상의한다",
      "options": [
        {
          "id": "a",
          "label": "전혀 아니다",
          "score": 0
        },
        {
          "id": "b",
          "label": "아니다",
          "score": 1
        },
        {
          "id": "c",
          "label": "보통이다",
          "score": 2
        },
        {
          "id": "d",
          "label": "그렇다",
          "score": 3
        },
        {
          "id": "e",
          "label": "매우 그렇다",
          "score": 4
        }
      ]
    },
    {
      "id": "q10",
      "text": "함께할 취미/루틴을 만들려 한다",
      "options": [
        {
          "id": "a",
          "label": "전혀 아니다",
          "score": 0
        },
        {
          "id": "b",
          "label": "아니다",
          "score": 1
        },
        {
          "id": "c",
          "label": "보통이다",
          "score": 2
        },
        {
          "id": "d",
          "label": "그렇다",
          "score": 3
        },
        {
          "id": "e",
          "label": "매우 그렇다",
          "score": 4
        }
      ]
    },
    {
      "id": "q11",
      "text": "장기 계획(여행·목표)을 함께 그린다",
      "options": [
        {
          "id": "a",
          "label": "전혀 아니다",
          "score": 0
        },
        {
          "id": "b",
          "label": "아니다",
          "score": 1
        },
        {
          "id": "c",
          "label": "보통이다",
          "score": 2
        },
        {
          "id": "d",
          "label": "그렇다",
          "score": 3
        },
        {
          "id": "e",
          "label": "매우 그렇다",
          "score": 4
        }
      ]
    },
    {
      "id": "q12",
      "text": "서로의 휴식 시간도 스케줄링한다",
      "options": [
        {
          "id": "a",
          "label": "전혀 아니다",
          "score": 0
        },
        {
          "id": "b",
          "label": "아니다",
          "score": 1
        },
        {
          "id": "c",
          "label": "보통이다",
          "score": 2
        },
        {
          "id": "d",
          "label": "그렇다",
          "score": 3
        },
        {
          "id": "e",
          "label": "매우 그렇다",
          "score": 4
        }
      ]
    }
  ],
  "results": [
    {
      "range": [
        0,
        12
      ],
      "label": "기초 다지기",
      "desc": "관계의 기본 공략법부터 쌓는 단계. 질문·피드백·경계 설정을 습관화."
    },
    {
      "range": [
        13,
        22
      ],
      "label": "안정 구축",
      "desc": "연락·약속·경계를 안정화. 갈등 규칙을 합의하면 비약적으로 좋아집니다."
    },
    {
      "range": [
        23,
        32
      ],
      "label": "성장 파트너",
      "desc": "함께 배우며 성장하는 전략형. 장기 계획을 가볍게 시도해 보세요."
    },
    {
      "range": [
        33,
        42
      ],
      "label": "리드 설계자",
      "desc": "관계 설계와 실행력이 탁월. 상대의 속도·휴식권을 더 존중하면 완성형."
    },
    {
      "range": [
        43,
        48
      ],
      "label": "마스터 전략가",
      "desc": "초반부터 고도화된 전략 운용. 과몰입 방지를 위한 ‘루틴/개인시간’ 분리가 핵심."
    }
  ],
  "scoring": {
    "option_scores": [
      0,
      1,
      2,
      3,
      4
    ],
    "sum": true
  },
  "disclaimer": "본 테스트는 엔터테인먼트/자가점검용이며, 전문적 진단이 아닙니다."
}